{
  "workData": [
    {
      "images": [
        "/images/work/davidson-homes/desktop.jpg",
        "/images/work/davidson-homes/desktop1.jpg",
        "/images/work/davidson-homes/desktop2.jpg",
        "/images/work/davidson-homes/mobile.jpg"
      ],
      "title": "Davidson Homes",
      "client": "Davidson Homes",
      "slug": "https://www.davidsonhomes.com/"
    },
    {
      "images": [
        "/images/work/decor-systems/desktop.jpg",
        "/images/work/decor-systems/mobile.jpg"
      ],
      "title": "Decor Systems",
      "client": "Decor Systems",
      "slug": "https://decorsystems.com.au/"
    },
    {
      "images": [
        "/images/work/karl-tatler/desktop.jpg",
        "/images/work/karl-tatler/listing-view.jpg",
        "/images/work/karl-tatler/map-view.jpg",
        "/images/work/karl-tatler/mobile.jpg"
      ],
      "title": "Karl Tatler",
      "client": "Karl Tatler",
      "slug": "https://www.karltatler.com/"
    },
    {
      "images": [
        "/images/work/liftiq/desktop.webp"
      ],
      "title": "LiftIQ",
      "client": "LiftIQ",
      "slug": "https://app.liftiq.com.au"
    },
    {
      "images": [
        "/images/work/nebessa/desktop.jpg"
      ],
      "title": "Nebessa",
      "client": "Nebessa",
      "slug": "https://nebessa.rs/"
    },
    {
      "images": [
        "/images/work/photoscoper/desktop.png",
        "/images/work/photoscoper/mobile.png",
        "/images/work/photoscoper/ui-design.png"
      ],
      "title": "Photoscoper",
      "client": "Photoscoper",
      "slug": "https://www.photoscoper.co.uk/"
    }
  ]
}
